Metadata-Version: 2.0
Name: odoo9-addon-account-payment-order
Version: 9.0.1.3.0
Summary: Account Payment Order
Home-page: https://github.com/OCA/bank-payment
Author: ACSONE SA/NV, Therp BV, Tecnativa, Akretion, Odoo Community Association (OCA)
Author-email: support@odoo-community.org
License: AGPL-3
Platform: UNKNOWN
Classifier: Programming Language :: Python :: 2.7
Classifier: Framework :: Odoo
Classifier: License :: OSI Approved :: GNU Affero General Public License v3
Requires-Dist: odoo (<9.1a,>=9.0a)
Requires-Dist: odoo9-addon-account-payment-partner
